dash_datatables/DashDatatables.py
dash_datatables/__init__.py
dash_datatables/_imports_.py
dash_datatables/dash_datatables.dev.js
dash_datatables/dash_datatables.dev.js.map
dash_datatables/dash_datatables.min.js
dash_datatables/dash_datatables.min.js.map
dash_datatables/metadata.json
dash_datatables/package-info.json
demo/__init__.py
demo/editable.py
demo/employees.py
demo/solar.py
demo/spa.py
demo/editable_table/__init__.py
demo/editable_table/editable.py
demo/editable_table/editable_form.py
demo/editable_table/editable_table.py
demo/editable_table/employee_list.py
tests/__init__.py
tests/test_usage.py
dash_datatables-0.0.9.dist-info/LICENSE
dash_datatables-0.0.9.dist-info/METADATA
dash_datatables-0.0.9.dist-info/WHEEL
dash_datatables-0.0.9.dist-info/top_level.txt
dash_datatables-0.0.9.dist-info/RECORD
